{
    "/js/cards.view~decks.browse~decks.mine~user.profile.decks.min.js": "/js/cards.view~decks.browse~decks.mine~user.profile.decks.min.js?id=8dbbba1972c82e7c91b7",
    "/js/vendors~cards.view~decks.build~decks.view.min.js": "/js/vendors~cards.view~decks.build~decks.view.min.js?id=8c71ba4f55c2ff09bb85",
    "/js/vendors~cards.view~home.min.js": "/js/vendors~cards.view~home.min.js?id=a86c12005cddbf3eff61",
    "/js/vendors~decks.build~events.edit.min.js": "/js/vendors~decks.build~events.edit.min.js?id=d1f432131736292a4823",
    "/js/cards.advanced.min.js": "/js/cards.advanced.min.js?id=c0cee7999970ffcf3171",
    "/js/cards.view.min.js": "/js/cards.view.min.js?id=8ba66470f1065e56c31e",
    "/js/decks.build~decks.view.min.js": "/js/decks.build~decks.view.min.js?id=ec4d77df79e3ed7efff7",
    "/js/events.edit.min.js": "/js/events.edit.min.js?id=10c37bc4ff7570868613",
    "/js/vendors~events.edit.min.js": "/js/vendors~events.edit.min.js?id=94b9265348d8d079a227",
    "/js/app.min.js": "/js/app.min.js?id=dfd3a458c910d8ede791",
    "/css/fabdb.min.css": "/css/fabdb.min.css?id=fe23f11ce886ac96c004",
    "/js/embed.min.js": "/js/embed.min.js?id=5a97c6183b37062bddfd",
    "/js/articles.spoilers.min.js": "/js/articles.spoilers.min.js?id=8187b0b98d2c543fc469",
    "/js/articles.view.min.js": "/js/articles.view.min.js?id=4966816530605081e734",
    "/js/artists.view.min.js": "/js/artists.view.min.js?id=501e61117e8b0ebec514",
    "/js/auth.login.min.js": "/js/auth.login.min.js?id=4cad0c829d94a3e93c72",
    "/js/auth.logout.min.js": "/js/auth.logout.min.js?id=7105d43ed0509f8127e0",
    "/js/cards.browse.min.js": "/js/cards.browse.min.js?id=b65095b18beb2f96db11",
    "/js/cards.fabled.min.js": "/js/cards.fabled.min.js?id=611f9085ceb90bd4af1c",
    "/js/collection.min.js": "/js/collection.min.js?id=31559c13bbac7fe66ac8",
    "/js/decks.browse.min.js": "/js/decks.browse.min.js?id=f3fb04aa5d5cec6e06e3",
    "/js/decks.build.min.js": "/js/decks.build.min.js?id=181eeeb38694afbe2c7a",
    "/js/decks.export.min.js": "/js/decks.export.min.js?id=7a8f3dc0adbb7c4c3bae",
    "/js/decks.featured.min.js": "/js/decks.featured.min.js?id=ecc2cc7898a528e25899",
    "/js/decks.mine.min.js": "/js/decks.mine.min.js?id=6a85888b6e87755be479",
    "/js/decks.starters.min.js": "/js/decks.starters.min.js?id=c29562c7cb585c018632",
    "/js/decks.test.min.js": "/js/decks.test.min.js?id=a1cb81acf5cf2e177cb6",
    "/js/decks.test.main.min.js": "/js/decks.test.main.min.js?id=4bfa1e93d80b3f3b5d1f",
    "/js/decks.view.min.js": "/js/decks.view.min.js?id=366b66d46f15a1091d1c",
    "/js/events.mine.min.js": "/js/events.mine.min.js?id=2301909da67c3947a3d0",
    "/js/events.view.min.js": "/js/events.view.min.js?id=aac99290a87c4895fb90",
    "/js/generator.min.js": "/js/generator.min.js?id=89cfb33eb076fb36bce5",
    "/js/home.min.js": "/js/home.min.js?id=068c78e5da93b9b72a51",
    "/js/practise.min.js": "/js/practise.min.js?id=9f9cbc064bd7bafe1d54",
    "/js/practise.setup.min.js": "/js/practise.setup.min.js?id=84e9eb825809ac46000e",
    "/js/practise.view.min.js": "/js/practise.view.min.js?id=1fc54f1dba7a50eddab5",
    "/js/premium.min.js": "/js/premium.min.js?id=2f4bbb138688afa8a713",
    "/js/privacy.min.js": "/js/privacy.min.js?id=c1f6667a5bf6bf8f013d",
    "/js/profile.min.js": "/js/profile.min.js?id=e204c1d1649e43a38bed",
    "/js/resources.api.min.js": "/js/resources.api.min.js?id=a4fc3009518c68e168a1",
    "/js/support.min.js": "/js/support.min.js?id=baf3ec653ab8d773de94",
    "/js/tools.counter.min.js": "/js/tools.counter.min.js?id=44f17e175c47318d5316",
    "/js/user.profile.decks.min.js": "/js/user.profile.decks.min.js?id=fb4b9059ee3b52671da1",
    "/js/user.profile.view.min.js": "/js/user.profile.view.min.js?id=7776608259d0c381c868",
    "/js/user.profile.wants.min.js": "/js/user.profile.wants.min.js?id=e5cb2d0436e7ed0cd3bf"
}
